parscript/__init__.py
parscript/dispatcher.py
parscript/worker.py
parscript-0.0.2.dist-info/DESCRIPTION.rst
parscript-0.0.2.dist-info/METADATA
parscript-0.0.2.dist-info/RECORD
parscript-0.0.2.dist-info/WHEEL
parscript-0.0.2.dist-info/metadata.json
parscript-0.0.2.dist-info/top_level.txt
