Metadata-Version: 2.0
Name: parscript
Version: 0.0.2
Summary: Parallel or distributed execution of jobs
Home-page: https://github.com/mtli/parscript
Author: Mengtian (Martin) Li
Author-email: martinli.work@gmail.com
License: MIT
Keywords: parallel computing distributed computing
Platform: UNKNOWN
Classifier: Development Status :: 3 - Alpha
Classifier: Intended Audience :: Science/Research
Classifier: Topic :: System :: Distributed Computing
Classifier: Topic :: Scientific/Engineering
Classifier: License :: OSI Approved :: MIT License
Classifier: Programming Language :: Python :: 2
Classifier: Programming Language :: Python :: 3
Classifier: Environment :: Console
Requires-Dist: portalocker
